{
  "meta": {
    "url": "https://www.fpcnv.be/jobs/",
    "path": "/jobs",
    "title": "jobs",
    "images": [
      "jobs.jpg",
      "fpc-gebouw.jpg"
    ]
  },
  "content": {
    "raw_text": "Jobs Home Â» Jobs Job in de kijker VerpleegkundigeMeer lezen Vacatures We hebben momenteel geen openstaande vacatures in de behandeling. Houd de website in de gaten of solliciteer spontaan.We hebben momenteel geen openstaande vacatures in de dienstverlening. Houd de website in de gaten of solliciteer spontaan.We hebben momenteel geen openstaande vacatures in de management. Houd de website in de gaten of solliciteer spontaan.We hebben momenteel geen openstaande vacatures. Houd de website in de gaten of solliciteer spontaan. Arbeidstherapeut (tuin) Behandeling FPC Antwerpen Meer lezen Groepsbegeleider/ Therapeutisch assistent Behandeling FPC Gent Meer lezen HR Medewerker Niet-zorg FPC Antwerpen Meer lezen Interne Auditor (m/v/x) voor het structureel uitvoeren van interne audits in FPC Antwerpen (interne vacature) N/A FPC Antwerpen Meer lezen Medewerker activiteiten dagelijks leven m/v/x (vervangingscontract) Behandeling FPC Antwerpen Meer lezen Medewerker bedrijfsopvangteam (BOT) (Interne vacature) Behandeling FPC Antwerpen Meer lezen Psychiater (m/v/x) Behandeling FPC Gent Meer lezen Psycholoog behandelaanbod en diagnostiek (m/v/x) Vervangingsovereenkomst Behandeling FPC Antwerpen Meer lezen Psychomotorisch therapeut / Bewegings-of Lichaamsgericht therapeut (m/v/x) Behandeling FPC Antwerpen Meer lezen Therapeutisch assistent ZIZ (zeer intensieve zorg) FPC Gent Meer lezen Verpleegkundige Behandeling FPC Antwerpen Meer lezen Verpleegkundige Behandeling FPC Gent Meer lezen Verpleegkundige ZIZ (zeer intensieve zorg) Behandeling FPC Gent Meer lezen Het video element wordt niet ondersteund door uw browser. Kiezen voor FPC Antwerpen of FPC GentAan de slag inCollega's getuigenSpontaan solliciterenStagesSollicitatieprocedure",
    "sections": [
      {
        "type": "hero",
        "content": {
          "titel": "Job in de kijker",
          "tagline": "Verpleegkundige",
          "cta_text": "Meer lezen"
        }
      },
      {
        "type": "text_block",
        "content": {
          "titel": "Vacatures",
          "tekst": "We hebben momenteel geen openstaande vacatures in de behandeling. Houd de website in de gaten of solliciteer spontaan.We hebben momenteel geen openstaande vacatures in de dienstverlening. Houd de website in de gaten of solliciteer spontaan.We hebben momenteel geen openstaande vacatures in de management. Houd de website in de gaten of solliciteer spontaan.We hebben momenteel geen openstaande vacatures. Houd de website in de gaten of solliciteer spontaan."
        }
      },
      {
        "type": "features",
        "content": {
          "titel": "Actuele Vacatures",
          "items": [
            {
              "titel": "Arbeidstherapeut (tuin)",
              "beschrijving": "Behandeling FPC Antwerpen Meer lezen",
              "icoon": ""
            },
            {
              "titel": "Groepsbegeleider/ Therapeutisch assistent",
              "beschrijving": "Behandeling FPC Gent Meer lezen",
              "icoon": ""
            },
            {
              "titel": "HR Medewerker",
              "beschrijving": "Niet-zorg FPC Antwerpen Meer lezen",
              "icoon": ""
            },
            {
              "titel": "Interne Auditor (m/v/x) voor het structureel uitvoeren van interne audits in FPC Antwerpen (interne vacature)",
              "beschrijving": "N/A FPC Antwerpen Meer lezen",
              "icoon": ""
            },
            {
              "titel": "Medewerker activiteiten dagelijks leven m/v/x (vervangingscontract)",
              "beschrijving": "Behandeling FPC Antwerpen Meer lezen",
              "icoon": ""
            },
            {
              "titel": "Medewerker bedrijfsopvangteam (BOT) (Interne vacature)",
              "beschrijving": "Behandeling FPC Antwerpen Meer lezen",
              "icoon": ""
            },
            {
              "titel": "Psychiater (m/v/x)",
              "beschrijving": "Behandeling FPC Gent Meer lezen",
              "icoon": ""
            },
            {
              "titel": "Psycholoog behandelaanbod en diagnostiek (m/v/x)",
              "beschrijving": "Vervangingsovereenkomst Behandeling FPC Antwerpen Meer lezen",
              "icoon": ""
            },
            {
              "titel": "Psychomotorisch therapeut / Bewegings-of Lichaamsgericht therapeut (m/v/x)",
              "beschrijving": "Behandeling FPC Antwerpen Meer lezen",
              "icoon": ""
            },
            {
              "titel": "Therapeutisch assistent ZIZ (zeer intensieve zorg)",
              "beschrijving": "FPC Gent Meer lezen",
              "icoon": ""
            },
            {
              "titel": "Verpleegkundige",
              "beschrijving": "Behandeling FPC Antwerpen Meer lezen",
              "icoon": ""
            },
            {
              "titel": "Verpleegkundige",
              "beschrijving": "Behandeling FPC Gent Meer lezen",
              "icoon": ""
            },
            {
              "titel": "Verpleegkundige ZIZ (zeer intensieve zorg)",
              "beschrijving": "Behandeling FPC Gent Meer lezen",
              "icoon": ""
            }
          ]
        }
      },
      {
        "type": "text_block",
        "content": {
          "titel": "Browsermelding",
          "tekst": "Het video element wordt niet ondersteund door uw browser."
        }
      },
      {
        "type": "list",
        "content": {
          "titel": "Meer informatie over werken bij FPC",
          "items": [
            "Kiezen voor FPC Antwerpen of FPC Gent",
            "Aan de slag in",
            "Collega's getuigen",
            "Spontaan solliciteren",
            "Stages",
            "Sollicitatieprocedure"
          ]
        }
      }
    ]
  }
}